Workbook

Sheet Dashboard
A1: RFQ & Supplier Quotation Evaluation Dashboard
A2: Illustrative procurement scenario | Currency: SAR | All sample records are fictional.
A4: RFQs Tracked | C4: Quotations Received | E4: Compliant Quotations | G4: Approved Requisitions
A5: =COUNTA('RFQ Register'!A5:A100) -> 12 | C5: =COUNTIF('RFQ Register'!G5:G100,"Received") -> 10 | E5: =COUNTIF('Quotation Comparison'!M5:M100,"Yes") -> 8 | G5: =COUNTIF('Purchase Requisitions'!L5:L100,"Approved") -> 6
A9: Requisition ID | B9: Item / Service | C9: Quotes Received | D9: Compliant Quotes | E9: Lowest Compliant Cost (SAR) | F9: Recommended Supplier | G9: Status
A10: PR-2026-001 | B10: Industrial Safety Gloves | C10: =COUNTIF('RFQ Register'!$B$5:$B$100,A10) -> 3 | D10: =COUNTIFS('Quotation Comparison'!$B$5:$B$100,A10,'Quotation Comparison'!$M$5:$M$100,"Yes") -> 2 | E10: =IFERROR(_xlfn.MINIFS('Quotation Comparison'!$J$5:$J$100,'Quotation Comparison'!$B$5:$B$100,A10,'Quotation Comparison'!$M$5:$M$100,"Yes",'Quotation Comparison'!$Q$5:$Q$100,"Eligible"),"") -> 4895.7 | F10: =IFERROR(INDEX('Award Recommendation'!$C$5:$C$20,MATCH(A10,'Award Recommendation'!$A$5:$A$20,0)),"Review Required") -> Eastern Safety Trading | G10: =IF(C10=0,"No Quotes",IF(D10=0,"Review Required","Evaluation Available")) -> Evaluation Available
A11: PR-2026-002 | B11: LED High-Bay Lights | C11: =COUNTIF('RFQ Register'!$B$5:$B$100,A11) -> 3 | D11: =COUNTIFS('Quotation Comparison'!$B$5:$B$100,A11,'Quotation Comparison'!$M$5:$M$100,"Yes") -> 2 | E11: =IFERROR(_xlfn.MINIFS('Quotation Comparison'!$J$5:$J$100,'Quotation Comparison'!$B$5:$B$100,A11,'Quotation Comparison'!$M$5:$M$100,"Yes",'Quotation Comparison'!$Q$5:$Q$100,"Eligible"),"") -> 16668.6 | F11: =IFERROR(INDEX('Award Recommendation'!$C$5:$C$20,MATCH(A11,'Award Recommendation'!$A$5:$A$20,0)),"Review Required") -> BrightTech Electrical | G11: =IF(C11=0,"No Quotes",IF(D11=0,"Review Required","Evaluation Available")) -> Evaluation Available
A12: PR-2026-003 | B12: Wireless Barcode Scanners | C12: =COUNTIF('RFQ Register'!$B$5:$B$100,A12) -> 3 | D12: =COUNTIFS('Quotation Comparison'!$B$5:$B$100,A12,'Quotation Comparison'!$M$5:$M$100,"Yes") -> 2 | E12: =IFERROR(_xlfn.MINIFS('Quotation Comparison'!$J$5:$J$100,'Quotation Comparison'!$B$5:$B$100,A12,'Quotation Comparison'!$M$5:$M$100,"Yes",'Quotation Comparison'!$Q$5:$Q$100,"Eligible"),"") -> 8715 | F12: =IFERROR(INDEX('Award Recommendation'!$C$5:$C$20,MATCH(A12,'Award Recommendation'!$A$5:$A$20,0)),"Review Required") -> ScanPro Systems | G12: =IF(C12=0,"No Quotes",IF(D12=0,"Review Required","Evaluation Available")) -> Evaluation Available
A13: PR-2026-005 | B13: Industrial Bearings | C13: =COUNTIF('RFQ Register'!$B$5:$B$100,A13) -> 3 | D13: =COUNTIFS('Quotation Comparison'!$B$5:$B$100,A13,'Quotation Comparison'!$M$5:$M$100,"Yes") -> 2 | E13: =IFERROR(_xlfn.MINIFS('Quotation Comparison'!$J$5:$J$100,'Quotation Comparison'!$B$5:$B$100,A13,'Quotation Comparison'!$M$5:$M$100,"Yes",'Quotation Comparison'!$Q$5:$Q$100,"Eligible"),"") -> 3730.8 | F13: =IFERROR(INDEX('Award Recommendation'!$C$5:$C$20,MATCH(A13,'Award Recommendation'!$A$5:$A$20,0)),"Review Required") -> Gulf Industrial Supply | G13: =IF(C13=0,"No Quotes",IF(D13=0,"Review Required","Evaluation Available")) -> Evaluation Available
A16: How to use
A17: 1. Review Purchase Requisitions and update request details and statuses.
A18: 2. Track supplier invitations and responses in RFQ Register.
A19: 3. Enter supplier quotations in Quotation Comparison; formulas calculate total cost and eligibility.
A20: 4. Review Supplier Evaluation and adjust documented score inputs where justified.
A21: 5. Use Award Recommendation as a decision-support summary, then obtain authorized approval.
A22: 6. All data are fictional examples; validate VAT, procurement policy, and scoring rules before real use.

Sheet Purchase Requisitions
A1: Purchase Requisitions
A2: Register internal purchase requests before sourcing suppliers. Sample data is illustrative; replace it with your own records.
A4: Requisition ID | B4: Request Date | C4: Requesting Department | D4: Requested By | E4: Item / Service Description | F4: Category | G4: Specification / Required Standard | H4: Quantity | I4: Unit | J4: Required By Date | K4: Priority | L4: Requisition Status | M4: Budget Code | N4: Notes
A5: PR-2026-001 | B5: 2026-09-02 | C5: Maintenance | D5: L. Carter | E5: Industrial Safety Gloves | F5: PPE | G5: EN 388 compliant; size mix specified | H5: 240 | I5: Pair | J5: 2026-09-18 | K5: High | L5: Approved | M5: MNT- PPE-01 | N5: Routine replenishment
A6: PR-2026-002 | B6: 2026-09-03 | C6: Facilities | D6: A. Morgan | E6: LED High-Bay Lights | F6: Electrical | G6: 150W LED; 5000K; minimum 20,000 lm | H6: 36 | I6: Each | J6: 2026-09-25 | K6: Normal | L6: Approved | M6: FAC-ELE-04 | N6: Replace failed warehouse fixtures
A7: PR-2026-003 | B7: 2026-09-04 | C7: IT | D7: J. Wilson | E7: Wireless Barcode Scanners | F7: IT Equipment | G7: 2D scanning; USB/Bluetooth; warranty required | H7: 12 | I7: Each | J7: 2026-09-28 | K7: High | L7: Approved | M7: IT-HW-02 | N7: For receiving and inventory teams
A8: PR-2026-004 | B8: 2026-09-05 | C8: Operations | D8: R. Patel | E8: Stretch Wrap Film | F8: Packaging | G8: 500 mm width; 23 micron; clear | H8: 180 | I8: Roll | J8: 2026-09-20 | K8: Normal | L8: Submitted | M8: OPS-PKG-03 | N8: Monthly packaging requirement
A9: PR-2026-005 | B9: 2026-09-06 | C9: Maintenance | D9: L. Carter | E9: Industrial Bearings | F9: MRO | G9: 6205-2RS; manufacturer traceability required | H9: 80 | I9: Each | J9: 2026-09-30 | K9: Critical | L9: Approved | M9: MNT-MRO-07 | N9: Equipment maintenance requirement
A10: PR-2026-006 | B10: 2026-09-08 | C10: Facilities | D10: A. Morgan | E10: Industrial Cleaning Detergent | F10: Cleaning Supplies | G10: Concentrated formula; safety data sheet required | H10: 60 | I10: Can | J10: 2026-09-22 | K10: Low | L10: Submitted | M10: FAC-CLN-02 | N10: Monthly facility supplies
A11: PR-2026-007 | B11: 2026-09-09 | C11: Operations | D11: R. Patel | E11: Pallets - Heat Treated | F11: Logistics Supplies | G11: 1200 x 1000 mm; ISPM 15 compliant | H11: 50 | I11: Each | J11: 2026-10-02 | K11: Normal | L11: Approved | M11: OPS-LOG-05 | N11: For export-ready storage
A12: PR-2026-008 | B12: 2026-09-10 | C12: IT | D12: J. Wilson | E12: UPS Battery Replacement Kit | F12: IT Equipment | G12: Compatible with existing UPS model; 12-month warranty | H12: 8 | I12: Kit | J12: 2026-09-29 | K12: High | L12: Approved | M12: IT-HW-05 | N12: Backup power maintenance

Sheet RFQ Register
A1: RFQ Register
A2: Track supplier invitations, responses, quotation validity, and follow-up actions.
A4: RFQ ID | B4: Requisition ID | C4: Supplier ID | D4: Supplier Name | E4: RFQ Sent Date | F4: Response Due Date | G4: Supplier Response | H4: Quotation Received Date | I4: Quoted Valid Until | J4: RFQ Status | K4: Follow-up Owner | L4: Follow-up Notes
A5: RFQ-2026-001 | B5: PR-2026-001 | C5: SUP-001 | D5: Gulf Industrial Supply | E5: 2026-09-03 | F5: 2026-09-08 | G5: Received | H5: 2026-09-07 | I5: 2026-10-07 | J5: Responses Received | K5: L. Carter | L5: Complete quotation received
A6: RFQ-2026-002 | B6: PR-2026-001 | C6: SUP-002 | D6: Eastern Safety Trading | E6: 2026-09-03 | F6: 2026-09-08 | G6: Received | H6: 2026-09-08 | I6: 2026-10-08 | J6: Responses Received | K6: L. Carter | L6: Quotation received on due date
A7: RFQ-2026-003 | B7: PR-2026-001 | C7: SUP-003 | D7: ProShield Supplies | E7: 2026-09-03 | F7: 2026-09-08 | G7: Received | H7: 2026-09-06 | I7: 2026-10-06 | J7: Responses Received | K7: L. Carter | L7: Alternative brand offered; verify compliance
A8: RFQ-2026-004 | B8: PR-2026-002 | C8: SUP-004 | D8: BrightTech Electrical | E8: 2026-09-05 | F8: 2026-09-11 | G8: Received | H8: 2026-09-10 | I8: 2026-10-10 | J8: Responses Received | K8: A. Morgan | L8: Complete quotation received
A9: RFQ-2026-005 | B9: PR-2026-002 | C9: SUP-005 | D9: Al Noor Lighting | E9: 2026-09-05 | F9: 2026-09-11 | G9: Received | H9: 2026-09-11 | I9: 2026-10-11 | J9: Responses Received | K9: A. Morgan | L9: Quotation received on due date
A10: RFQ-2026-006 | B10: PR-2026-002 | C10: SUP-006 | D10: Modern Light Solutions | E10: 2026-09-05 | F10: 2026-09-11 | G10: Pending | K10: A. Morgan | L10: Follow up before due date
A11: RFQ-2026-007 | B11: PR-2026-003 | C11: SUP-007 | D11: ScanPro Systems | E11: 2026-09-06 | F11: 2026-09-13 | G11: Received | H11: 2026-09-12 | I11: 2026-10-12 | J11: Responses Received | K11: J. Wilson | L11: Complete quotation received
A12: RFQ-2026-008 | B12: PR-2026-003 | C12: SUP-008 | D12: TechRoute Trading | E12: 2026-09-06 | F12: 2026-09-13 | G12: Received | H12: 2026-09-13 | I12: 2026-10-13 | J12: Responses Received | K12: J. Wilson | L12: Warranty term requires review
A13: RFQ-2026-009 | B13: PR-2026-003 | C13: SUP-009 | D13: Digital Supply House | E13: 2026-09-06 | F13: 2026-09-13 | G13: Declined | K13: J. Wilson | L13: Supplier declined to quote
A14: RFQ-2026-010 | B14: PR-2026-005 | C14: SUP-001 | D14: Gulf Industrial Supply | E14: 2026-09-07 | F14: 2026-09-12 | G14: Received | H14: 2026-09-11 | I14: 2026-10-11 | J14: Responses Received | K14: L. Carter | L14: Complete quotation received
A15: RFQ-2026-011 | B15: PR-2026-005 | C15: SUP-010 | D15: Bearing World | E15: 2026-09-07 | F15: 2026-09-12 | G15: Received | H15: 2026-09-12 | I15: 2026-10-12 | J15: Responses Received | K15: L. Carter | L15: Confirm manufacturer traceability
A16: RFQ-2026-012 | B16: PR-2026-005 | C16: SUP-011 | D16: Precision MRO | E16: 2026-09-07 | F16: 2026-09-12 | G16: Received | H16: 2026-09-10 | I16: 2026-10-10 | J16: Responses Received | K16: L. Carter | L16: Complete quotation received

Sheet Quotation Comparison
A1: Quotation Comparison
A2: Compare supplier quotations on a like-for-like basis. Total cost includes discount, shipping, and VAT; confirm tax treatment before real use.
A4: RFQ ID | B4: Requisition ID | C4: Supplier ID | D4: Supplier Name | E4: Quoted Unit Price (SAR) | F4: Quantity | G4: Discount (%) | H4: Shipping (SAR) | I4: VAT Rate (%) | J4: Total Quoted Cost (SAR) | K4: Lead Time (Days) | L4: Payment Terms (Days) | M4: Specification Compliant? | N4: Warranty (Months) | O4: Quotation Valid? | P4: Price Rank | Q4: Evaluation Status
A5: RFQ-2026-001 | B5: PR-2026-001 | C5: SUP-001 | D5: Gulf Industrial Supply | E5: 18.5 | F5: 240 | G5: 0.05 | H5: 45 | I5: 0.15 | J5: =IF(OR(E5="",F5=""),"",ROUND(E5*F5*(1-G5)*(1+I5)+H5,2)) -> 4895.7 | K5: 7 | L5: 30 | M5: Yes | N5: 12 | O5: =IF(A5="","",IFERROR(IF(INDEX('RFQ Register'!$I$5:$I$100,MATCH(A5,'RFQ Register'!$A$5:$A$100,0))>=TODAY(),"Yes","Expired"),"Pending Review")) -> Yes | P5: =IF(OR(J5="",Q5<>"Eligible"),"",COUNTIFS($B$5:$B$100,B5,$J$5:$J$100,"<"&J5,$Q$5:$Q$100,"Eligible")+1) -> 1 | Q5: =IF(A5="","",IF(M5="No","Non-Compliant",IF(M5="Pending","Pending Review",IF(O5="Expired","Expired",IF(O5="Yes","Eligible","Pending Review"))))) -> Eligible
A6: RFQ-2026-002 | B6: PR-2026-001 | C6: SUP-002 | D6: Eastern Safety Trading | E6: 17.9 | F6: 240 | G6: 0 | H6: 80 | I6: 0.15 | J6: =IF(OR(E6="",F6=""),"",ROUND(E6*F6*(1-G6)*(1+I6)+H6,2)) -> 5020.4 | K6: 5 | L6: 15 | M6: Yes | N6: 6 | O6: =IF(A6="","",IFERROR(IF(INDEX('RFQ Register'!$I$5:$I$100,MATCH(A6,'RFQ Register'!$A$5:$A$100,0))>=TODAY(),"Yes","Expired"),"Pending Review")) -> Yes | P6: =IF(OR(J6="",Q6<>"Eligible"),"",COUNTIFS($B$5:$B$100,B6,$J$5:$J$100,"<"&J6,$Q$5:$Q$100,"Eligible")+1) -> 2 | Q6: =IF(A6="","",IF(M6="No","Non-Compliant",IF(M6="Pending","Pending Review",IF(O6="Expired","Expired",IF(O6="Yes","Eligible","Pending Review"))))) -> Eligible
A7: RFQ-2026-003 | B7: PR-2026-001 | C7: SUP-003 | D7: ProShield Supplies | E7: 16.8 | F7: 240 | G7: 0.03 | H7: 120 | I7: 0.15 | J7: =IF(OR(E7="",F7=""),"",ROUND(E7*F7*(1-G7)*(1+I7)+H7,2)) -> 4617.7 | K7: 10 | L7: 45 | M7: No | N7: 12 | O7: =IF(A7="","",IFERROR(IF(INDEX('RFQ Register'!$I$5:$I$100,MATCH(A7,'RFQ Register'!$A$5:$A$100,0))>=TODAY(),"Yes","Expired"),"Pending Review")) -> Yes | P7: =IF(OR(J7="",Q7<>"Eligible"),"",COUNTIFS($B$5:$B$100,B7,$J$5:$J$100,"<"&J7,$Q$5:$Q$100,"Eligible")+1) | Q7: =IF(A7="","",IF(M7="No","Non-Compliant",IF(M7="Pending","Pending Review",IF(O7="Expired","Expired",IF(O7="Yes","Eligible","Pending Review"))))) -> Non-Compliant
A8: RFQ-2026-004 | B8: PR-2026-002 | C8: SUP-004 | D8: BrightTech Electrical | E8: 420 | F8: 36 | G8: 0.05 | H8: 150 | I8: 0.15 | J8: =IF(OR(E8="",F8=""),"",ROUND(E8*F8*(1-G8)*(1+I8)+H8,2)) -> 16668.6 | K8: 8 | L8: 30 | M8: Yes | N8: 36 | O8: =IF(A8="","",IFERROR(IF(INDEX('RFQ Register'!$I$5:$I$100,MATCH(A8,'RFQ Register'!$A$5:$A$100,0))>=TODAY(),"Yes","Expired"),"Pending Review")) -> Yes | P8: =IF(OR(J8="",Q8<>"Eligible"),"",COUNTIFS($B$5:$B$100,B8,$J$5:$J$100,"<"&J8,$Q$5:$Q$100,"Eligible")+1) -> 1 | Q8: =IF(A8="","",IF(M8="No","Non-Compliant",IF(M8="Pending","Pending Review",IF(O8="Expired","Expired",IF(O8="Yes","Eligible","Pending Review"))))) -> Eligible
A9: RFQ-2026-005 | B9: PR-2026-002 | C9: SUP-005 | D9: Al Noor Lighting | E9: 398 | F9: 36 | G9: 0 | H9: 250 | I9: 0.15 | J9: =IF(OR(E9="",F9=""),"",ROUND(E9*F9*(1-G9)*(1+I9)+H9,2)) -> 16727.2 | K9: 12 | L9: 45 | M9: Yes | N9: 24 | O9: =IF(A9="","",IFERROR(IF(INDEX('RFQ Register'!$I$5:$I$100,MATCH(A9,'RFQ Register'!$A$5:$A$100,0))>=TODAY(),"Yes","Expired"),"Pending Review")) -> Yes | P9: =IF(OR(J9="",Q9<>"Eligible"),"",COUNTIFS($B$5:$B$100,B9,$J$5:$J$100,"<"&J9,$Q$5:$Q$100,"Eligible")+1) -> 2 | Q9: =IF(A9="","",IF(M9="No","Non-Compliant",IF(M9="Pending","Pending Review",IF(O9="Expired","Expired",IF(O9="Yes","Eligible","Pending Review"))))) -> Eligible
A10: RFQ-2026-007 | B10: PR-2026-003 | C10: SUP-007 | D10: ScanPro Systems | E10: 680 | F10: 12 | G10: 0.02 | H10: 0 | I10: 0.15 | J10: =IF(OR(E10="",F10=""),"",ROUND(E10*F10*(1-G10)*(1+I10)+H10,2)) -> 9196.32 | K10: 5 | L10: 30 | M10: Yes | N10: 24 | O10: =IF(A10="","",IFERROR(IF(INDEX('RFQ Register'!$I$5:$I$100,MATCH(A10,'RFQ Register'!$A$5:$A$100,0))>=TODAY(),"Yes","Expired"),"Pending Review")) -> Yes | P10: =IF(OR(J10="",Q10<>"Eligible"),"",COUNTIFS($B$5:$B$100,B10,$J$5:$J$100,"<"&J10,$Q$5:$Q$100,"Eligible")+1) -> 2 | Q10: =IF(A10="","",IF(M10="No","Non-Compliant",IF(M10="Pending","Pending Review",IF(O10="Expired","Expired",IF(O10="Yes","Eligible","Pending Review"))))) -> Eligible
A11: RFQ-2026-008 | B11: PR-2026-003 | C11: SUP-008 | D11: TechRoute Trading | E11: 625 | F11: 12 | G11: 0 | H11: 90 | I11: 0.15 | J11: =IF(OR(E11="",F11=""),"",ROUND(E11*F11*(1-G11)*(1+I11)+H11,2)) -> 8715 | K11: 14 | L11: 60 | M11: Yes | N11: 12 | O11: =IF(A11="","",IFERROR(IF(INDEX('RFQ Register'!$I$5:$I$100,MATCH(A11,'RFQ Register'!$A$5:$A$100,0))>=TODAY(),"Yes","Expired"),"Pending Review")) -> Yes | P11: =IF(OR(J11="",Q11<>"Eligible"),"",COUNTIFS($B$5:$B$100,B11,$J$5:$J$100,"<"&J11,$Q$5:$Q$100,"Eligible")+1) -> 1 | Q11: =IF(A11="","",IF(M11="No","Non-Compliant",IF(M11="Pending","Pending Review",IF(O11="Expired","Expired",IF(O11="Yes","Eligible","Pending Review"))))) -> Eligible
A12: RFQ-2026-010 | B12: PR-2026-005 | C12: SUP-001 | D12: Gulf Industrial Supply | E12: 42 | F12: 80 | G12: 0.05 | H12: 60 | I12: 0.15 | J12: =IF(OR(E12="",F12=""),"",ROUND(E12*F12*(1-G12)*(1+I12)+H12,2)) -> 3730.8 | K12: 6 | L12: 30 | M12: Yes | N12: 12 | O12: =IF(A12="","",IFERROR(IF(INDEX('RFQ Register'!$I$5:$I$100,MATCH(A12,'RFQ Register'!$A$5:$A$100,0))>=TODAY(),"Yes","Expired"),"Pending Review")) -> Yes | P12: =IF(OR(J12="",Q12<>"Eligible"),"",COUNTIFS($B$5:$B$100,B12,$J$5:$J$100,"<"&J12,$Q$5:$Q$100,"Eligible")+1) -> 1 | Q12: =IF(A12="","",IF(M12="No","Non-Compliant",IF(M12="Pending","Pending Review",IF(O12="Expired","Expired",IF(O12="Yes","Eligible","Pending Review"))))) -> Eligible
A13: RFQ-2026-011 | B13: PR-2026-005 | C13: SUP-010 | D13: Bearing World | E13: 39.5 | F13: 80 | G13: 0 | H13: 95 | I13: 0.15 | J13: =IF(OR(E13="",F13=""),"",ROUND(E13*F13*(1-G13)*(1+I13)+H13,2)) -> 3729 | K13: 9 | L13: 30 | M13: Pending | N13: 12 | O13: =IF(A13="","",IFERROR(IF(INDEX('RFQ Register'!$I$5:$I$100,MATCH(A13,'RFQ Register'!$A$5:$A$100,0))>=TODAY(),"Yes","Expired"),"Pending Review")) -> Yes | P13: =IF(OR(J13="",Q13<>"Eligible"),"",COUNTIFS($B$5:$B$100,B13,$J$5:$J$100,"<"&J13,$Q$5:$Q$100,"Eligible")+1) | Q13: =IF(A13="","",IF(M13="No","Non-Compliant",IF(M13="Pending","Pending Review",IF(O13="Expired","Expired",IF(O13="Yes","Eligible","Pending Review"))))) -> Pending Review
A14: RFQ-2026-012 | B14: PR-2026-005 | C14: SUP-011 | D14: Precision MRO | E14: 41 | F14: 80 | G14: 0.02 | H14: 40 | I14: 0.15 | J14: =IF(OR(E14="",F14=""),"",ROUND(E14*F14*(1-G14)*(1+I14)+H14,2)) -> 3736.56 | K14: 7 | L14: 45 | M14: Yes | N14: 24 | O14: =IF(A14="","",IFERROR(IF(INDEX('RFQ Register'!$I$5:$I$100,MATCH(A14,'RFQ Register'!$A$5:$A$100,0))>=TODAY(),"Yes","Expired"),"Pending Review")) -> Yes | P14: =IF(OR(J14="",Q14<>"Eligible"),"",COUNTIFS($B$5:$B$100,B14,$J$5:$J$100,"<"&J14,$Q$5:$Q$100,"Eligible")+1) -> 2 | Q14: =IF(A14="","",IF(M14="No","Non-Compliant",IF(M14="Pending","Pending Review",IF(O14="Expired","Expired",IF(O14="Yes","Eligible","Pending Review"))))) -> Eligible
P15: =IF(OR(J15="",Q15<>"Eligible"),"",COUNTIFS($B$5:$B$100,B15,$J$5:$J$100,"<"&J15,$Q$5:$Q$100,"Eligible")+1)
P16: =IF(OR(J16="",Q16<>"Eligible"),"",COUNTIFS($B$5:$B$100,B16,$J$5:$J$100,"<"&J16,$Q$5:$Q$100,"Eligible")+1)
P17: =IF(OR(J17="",Q17<>"Eligible"),"",COUNTIFS($B$5:$B$100,B17,$J$5:$J$100,"<"&J17,$Q$5:$Q$100,"Eligible")+1)
P18: =IF(OR(J18="",Q18<>"Eligible"),"",COUNTIFS($B$5:$B$100,B18,$J$5:$J$100,"<"&J18,$Q$5:$Q$100,"Eligible")+1)
P19: =IF(OR(J19="",Q19<>"Eligible"),"",COUNTIFS($B$5:$B$100,B19,$J$5:$J$100,"<"&J19,$Q$5:$Q$100,"Eligible")+1)
P20: =IF(OR(J20="",Q20<>"Eligible"),"",COUNTIFS($B$5:$B$100,B20,$J$5:$J$100,"<"&J20,$Q$5:$Q$100,"Eligible")+1)
P21: =IF(OR(J21="",Q21<>"Eligible"),"",COUNTIFS($B$5:$B$100,B21,$J$5:$J$100,"<"&J21,$Q$5:$Q$100,"Eligible")+1)
P22: =IF(OR(J22="",Q22<>"Eligible"),"",COUNTIFS($B$5:$B$100,B22,$J$5:$J$100,"<"&J22,$Q$5:$Q$100,"Eligible")+1)
P23: =IF(OR(J23="",Q23<>"Eligible"),"",COUNTIFS($B$5:$B$100,B23,$J$5:$J$100,"<"&J23,$Q$5:$Q$100,"Eligible")+1)
P24: =IF(OR(J24="",Q24<>"Eligible"),"",COUNTIFS($B$5:$B$100,B24,$J$5:$J$100,"<"&J24,$Q$5:$Q$100,"Eligible")+1)
P25: =IF(OR(J25="",Q25<>"Eligible"),"",COUNTIFS($B$5:$B$100,B25,$J$5:$J$100,"<"&J25,$Q$5:$Q$100,"Eligible")+1)
P26: =IF(OR(J26="",Q26<>"Eligible"),"",COUNTIFS($B$5:$B$100,B26,$J$5:$J$100,"<"&J26,$Q$5:$Q$100,"Eligible")+1)
... P100: =IF(OR(J100="",Q100<>"Eligible"),"",COUNTIFS($B$5:$B$100,B100,$J$5:$J$100,"<"&J100,$Q$5:$Q$100,"Eligible")+1)

Sheet Supplier Evaluation
A1: Supplier Evaluation
A2: Weighted scoring is an illustrative decision aid. Compliance is a mandatory gate; a high score does not override non-compliance.
A4: Requisition ID | B4: Supplier ID | C4: Supplier Name | D4: Total Quoted Cost (SAR) | E4: Price Score (0-100) | F4: Lead Time (Days) | G4: Lead Time Score (0-100) | H4: Quality Score (0-100) | I4: Payment Terms Score (0-100) | J4: Weighted Score | K4: Compliance Gate | L4: Recommendation
A5: PR-2026-001 | B5: SUP-001 | C5: Gulf Industrial Supply | D5: =IFERROR(INDEX('Quotation Comparison'!$J$5:$J$100,MATCH(1,INDEX(('Quotation Comparison'!$B$5:$B$100=A5)*('Quotation Comparison'!$C$5:$C$100=B5),0),0)),"") -> 4895.7 | E5: =IF(K5<>"Yes","",IFERROR(MIN(100,_xlfn.MINIFS('Quotation Comparison'!$J$5:$J$100,'Quotation Comparison'!$B$5:$B$100,A5,'Quotation Comparison'!$M$5:$M$100,"Yes",'Quotation Comparison'!$Q$5:$Q$100,"Eligible")/D5*100),"")) -> 100 | F5: =IFERROR(INDEX('Quotation Comparison'!$K$5:$K$100,MATCH(1,INDEX(('Quotation Comparison'!$B$5:$B$100=A5)*('Quotation Comparison'!$C$5:$C$100=B5),0),0)),"") -> 7 | G5: =IF(K5<>"Yes","",IFERROR(MIN(100,_xlfn.MINIFS('Quotation Comparison'!$K$5:$K$100,'Quotation Comparison'!$B$5:$B$100,A5,'Quotation Comparison'!$M$5:$M$100,"Yes",'Quotation Comparison'!$Q$5:$Q$100,"Eligible")/F5*100),"")) -> 71.428571 | H5: 90 | I5: 80 | J5: =IF(K5<>"Yes","",IF(COUNT(E5,G5,H5,I5)<4,"",E5*30%+G5*25%+H5*25%+I5*20%)) -> 86.357143 | K5: =IFERROR(INDEX('Quotation Comparison'!$M$5:$M$100,MATCH(1,INDEX(('Quotation Comparison'!$B$5:$B$100=A5)*('Quotation Comparison'!$C$5:$C$100=B5),0),0)),"Pending") -> Yes | L5: =IF(K5<>"Yes","Not Eligible",IF(J5="","Pending Evaluation",IF(J5>=80,"Recommended for Review","Alternative for Review"))) -> Recommended for Review
A6: PR-2026-001 | B6: SUP-002 | C6: Eastern Safety Trading | D6: =IFERROR(INDEX('Quotation Comparison'!$J$5:$J$100,MATCH(1,INDEX(('Quotation Comparison'!$B$5:$B$100=A6)*('Quotation Comparison'!$C$5:$C$100=B6),0),0)),"") -> 5020.4 | E6: =IF(K6<>"Yes","",IFERROR(MIN(100,_xlfn.MINIFS('Quotation Comparison'!$J$5:$J$100,'Quotation Comparison'!$B$5:$B$100,A6,'Quotation Comparison'!$M$5:$M$100,"Yes",'Quotation Comparison'!$Q$5:$Q$100,"Eligible")/D6*100),"")) -> 97.516134 | F6: =IFERROR(INDEX('Quotation Comparison'!$K$5:$K$100,MATCH(1,INDEX(('Quotation Comparison'!$B$5:$B$100=A6)*('Quotation Comparison'!$C$5:$C$100=B6),0),0)),"") -> 5 | G6: =IF(K6<>"Yes","",IFERROR(MIN(100,_xlfn.MINIFS('Quotation Comparison'!$K$5:$K$100,'Quotation Comparison'!$B$5:$B$100,A6,'Quotation Comparison'!$M$5:$M$100,"Yes",'Quotation Comparison'!$Q$5:$Q$100,"Eligible")/F6*100),"")) -> 100 | H6: 85 | I6: 90 | J6: =IF(K6<>"Yes","",IF(COUNT(E6,G6,H6,I6)<4,"",E6*30%+G6*25%+H6*25%+I6*20%)) -> 93.50484 | K6: =IFERROR(INDEX('Quotation Comparison'!$M$5:$M$100,MATCH(1,INDEX(('Quotation Comparison'!$B$5:$B$100=A6)*('Quotation Comparison'!$C$5:$C$100=B6),0),0)),"Pending") -> Yes | L6: =IF(K6<>"Yes","Not Eligible",IF(J6="","Pending Evaluation",IF(J6>=80,"Recommended for Review","Alternative for Review"))) -> Recommended for Review
A7: PR-2026-001 | B7: SUP-003 | C7: ProShield Supplies | D7: =IFERROR(INDEX('Quotation Comparison'!$J$5:$J$100,MATCH(1,INDEX(('Quotation Comparison'!$B$5:$B$100=A7)*('Quotation Comparison'!$C$5:$C$100=B7),0),0)),"") -> 4617.7 | E7: =IF(K7<>"Yes","",IFERROR(MIN(100,_xlfn.MINIFS('Quotation Comparison'!$J$5:$J$100,'Quotation Comparison'!$B$5:$B$100,A7,'Quotation Comparison'!$M$5:$M$100,"Yes",'Quotation Comparison'!$Q$5:$Q$100,"Eligible")/D7*100),"")) | F7: =IFERROR(INDEX('Quotation Comparison'!$K$5:$K$100,MATCH(1,INDEX(('Quotation Comparison'!$B$5:$B$100=A7)*('Quotation Comparison'!$C$5:$C$100=B7),0),0)),"") -> 10 | G7: =IF(K7<>"Yes","",IFERROR(MIN(100,_xlfn.MINIFS('Quotation Comparison'!$K$5:$K$100,'Quotation Comparison'!$B$5:$B$100,A7,'Quotation Comparison'!$M$5:$M$100,"Yes",'Quotation Comparison'!$Q$5:$Q$100,"Eligible")/F7*100),"")) | H7: 88 | I7: 75 | J7: =IF(K7<>"Yes","",IF(COUNT(E7,G7,H7,I7)<4,"",E7*30%+G7*25%+H7*25%+I7*20%)) | K7: =IFERROR(INDEX('Quotation Comparison'!$M$5:$M$100,MATCH(1,INDEX(('Quotation Comparison'!$B$5:$B$100=A7)*('Quotation Comparison'!$C$5:$C$100=B7),0),0)),"Pending") -> No | L7: =IF(K7<>"Yes","Not Eligible",IF(J7="","Pending Evaluation",IF(J7>=80,"Recommended for Review","Alternative for Review"))) -> Not Eligible
A8: PR-2026-002 | B8: SUP-004 | C8: BrightTech Electrical | D8: =IFERROR(INDEX('Quotation Comparison'!$J$5:$J$100,MATCH(1,INDEX(('Quotation Comparison'!$B$5:$B$100=A8)*('Quotation Comparison'!$C$5:$C$100=B8),0),0)),"") -> 16668.6 | E8: =IF(K8<>"Yes","",IFERROR(MIN(100,_xlfn.MINIFS('Quotation Comparison'!$J$5:$J$100,'Quotation Comparison'!$B$5:$B$100,A8,'Quotation Comparison'!$M$5:$M$100,"Yes",'Quotation Comparison'!$Q$5:$Q$100,"Eligible")/D8*100),"")) -> 100 | F8: =IFERROR(INDEX('Quotation Comparison'!$K$5:$K$100,MATCH(1,INDEX(('Quotation Comparison'!$B$5:$B$100=A8)*('Quotation Comparison'!$C$5:$C$100=B8),0),0)),"") -> 8 | G8: =IF(K8<>"Yes","",IFERROR(MIN(100,_xlfn.MINIFS('Quotation Comparison'!$K$5:$K$100,'Quotation Comparison'!$B$5:$B$100,A8,'Quotation Comparison'!$M$5:$M$100,"Yes",'Quotation Comparison'!$Q$5:$Q$100,"Eligible")/F8*100),"")) -> 100 | H8: 92 | I8: 80 | J8: =IF(K8<>"Yes","",IF(COUNT(E8,G8,H8,I8)<4,"",E8*30%+G8*25%+H8*25%+I8*20%)) -> 94 | K8: =IFERROR(INDEX('Quotation Comparison'!$M$5:$M$100,MATCH(1,INDEX(('Quotation Comparison'!$B$5:$B$100=A8)*('Quotation Comparison'!$C$5:$C$100=B8),0),0)),"Pending") -> Yes | L8: =IF(K8<>"Yes","Not Eligible",IF(J8="","Pending Evaluation",IF(J8>=80,"Recommended for Review","Alternative for Review"))) -> Recommended for Review
A9: PR-2026-002 | B9: SUP-005 | C9: Al Noor Lighting | D9: =IFERROR(INDEX('Quotation Comparison'!$J$5:$J$100,MATCH(1,INDEX(('Quotation Comparison'!$B$5:$B$100=A9)*('Quotation Comparison'!$C$5:$C$100=B9),0),0)),"") -> 16727.2 | E9: =IF(K9<>"Yes","",IFERROR(MIN(100,_xlfn.MINIFS('Quotation Comparison'!$J$5:$J$100,'Quotation Comparison'!$B$5:$B$100,A9,'Quotation Comparison'!$M$5:$M$100,"Yes",'Quotation Comparison'!$Q$5:$Q$100,"Eligible")/D9*100),"")) -> 99.649672 | F9: =IFERROR(INDEX('Quotation Comparison'!$K$5:$K$100,MATCH(1,INDEX(('Quotation Comparison'!$B$5:$B$100=A9)*('Quotation Comparison'!$C$5:$C$100=B9),0),0)),"") -> 12 | G9: =IF(K9<>"Yes","",IFERROR(MIN(100,_xlfn.MINIFS('Quotation Comparison'!$K$5:$K$100,'Quotation Comparison'!$B$5:$B$100,A9,'Quotation Comparison'!$M$5:$M$100,"Yes",'Quotation Comparison'!$Q$5:$Q$100,"Eligible")/F9*100),"")) -> 66.666667 | H9: 88 | I9: 90 | J9: =IF(K9<>"Yes","",IF(COUNT(E9,G9,H9,I9)<4,"",E9*30%+G9*25%+H9*25%+I9*20%)) -> 86.561568 | K9: =IFERROR(INDEX('Quotation Comparison'!$M$5:$M$100,MATCH(1,INDEX(('Quotation Comparison'!$B$5:$B$100=A9)*('Quotation Comparison'!$C$5:$C$100=B9),0),0)),"Pending") -> Yes | L9: =IF(K9<>"Yes","Not Eligible",IF(J9="","Pending Evaluation",IF(J9>=80,"Recommended for Review","Alternative for Review"))) -> Recommended for Review
A10: PR-2026-003 | B10: SUP-007 | C10: ScanPro Systems | D10: =IFERROR(INDEX('Quotation Comparison'!$J$5:$J$100,MATCH(1,INDEX(('Quotation Comparison'!$B$5:$B$100=A10)*('Quotation Comparison'!$C$5:$C$100=B10),0),0)),"") -> 9196.32 | E10: =IF(K10<>"Yes","",IFERROR(MIN(100,_xlfn.MINIFS('Quotation Comparison'!$J$5:$J$100,'Quotation Comparison'!$B$5:$B$100,A10,'Quotation Comparison'!$M$5:$M$100,"Yes",'Quotation Comparison'!$Q$5:$Q$100,"Eligible")/D10*100),"")) -> 94.766167 | F10: =IFERROR(INDEX('Quotation Comparison'!$K$5:$K$100,MATCH(1,INDEX(('Quotation Comparison'!$B$5:$B$100=A10)*('Quotation Comparison'!$C$5:$C$100=B10),0),0)),"") -> 5 | G10: =IF(K10<>"Yes","",IFERROR(MIN(100,_xlfn.MINIFS('Quotation Comparison'!$K$5:$K$100,'Quotation Comparison'!$B$5:$B$100,A10,'Quotation Comparison'!$M$5:$M$100,"Yes",'Quotation Comparison'!$Q$5:$Q$100,"Eligible")/F10*100),"")) -> 100 | H10: 90 | I10: 85 | J10: =IF(K10<>"Yes","",IF(COUNT(E10,G10,H10,I10)<4,"",E10*30%+G10*25%+H10*25%+I10*20%)) -> 92.92985 | K10: =IFERROR(INDEX('Quotation Comparison'!$M$5:$M$100,MATCH(1,INDEX(('Quotation Comparison'!$B$5:$B$100=A10)*('Quotation Comparison'!$C$5:$C$100=B10),0),0)),"Pending") -> Yes | L10: =IF(K10<>"Yes","Not Eligible",IF(J10="","Pending Evaluation",IF(J10>=80,"Recommended for Review","Alternative for Review"))) -> Recommended for Review
A11: PR-2026-003 | B11: SUP-008 | C11: TechRoute Trading | D11: =IFERROR(INDEX('Quotation Comparison'!$J$5:$J$100,MATCH(1,INDEX(('Quotation Comparison'!$B$5:$B$100=A11)*('Quotation Comparison'!$C$5:$C$100=B11),0),0)),"") -> 8715 | E11: =IF(K11<>"Yes","",IFERROR(MIN(100,_xlfn.MINIFS('Quotation Comparison'!$J$5:$J$100,'Quotation Comparison'!$B$5:$B$100,A11,'Quotation Comparison'!$M$5:$M$100,"Yes",'Quotation Comparison'!$Q$5:$Q$100,"Eligible")/D11*100),"")) -> 100 | F11: =IFERROR(INDEX('Quotation Comparison'!$K$5:$K$100,MATCH(1,INDEX(('Quotation Comparison'!$B$5:$B$100=A11)*('Quotation Comparison'!$C$5:$C$100=B11),0),0)),"") -> 14 | G11: =IF(K11<>"Yes","",IFERROR(MIN(100,_xlfn.MINIFS('Quotation Comparison'!$K$5:$K$100,'Quotation Comparison'!$B$5:$B$100,A11,'Quotation Comparison'!$M$5:$M$100,"Yes",'Quotation Comparison'!$Q$5:$Q$100,"Eligible")/F11*100),"")) -> 35.714286 | H11: 85 | I11: 95 | J11: =IF(K11<>"Yes","",IF(COUNT(E11,G11,H11,I11)<4,"",E11*30%+G11*25%+H11*25%+I11*20%)) -> 79.178571 | K11: =IFERROR(INDEX('Quotation Comparison'!$M$5:$M$100,MATCH(1,INDEX(('Quotation Comparison'!$B$5:$B$100=A11)*('Quotation Comparison'!$C$5:$C$100=B11),0),0)),"Pending") -> Yes | L11: =IF(K11<>"Yes","Not Eligible",IF(J11="","Pending Evaluation",IF(J11>=80,"Recommended for Review","Alternative for Review"))) -> Alternative for Review
A12: PR-2026-005 | B12: SUP-001 | C12: Gulf Industrial Supply | D12: =IFERROR(INDEX('Quotation Comparison'!$J$5:$J$100,MATCH(1,INDEX(('Quotation Comparison'!$B$5:$B$100=A12)*('Quotation Comparison'!$C$5:$C$100=B12),0),0)),"") -> 3730.8 | E12: =IF(K12<>"Yes","",IFERROR(MIN(100,_xlfn.MINIFS('Quotation Comparison'!$J$5:$J$100,'Quotation Comparison'!$B$5:$B$100,A12,'Quotation Comparison'!$M$5:$M$100,"Yes",'Quotation Comparison'!$Q$5:$Q$100,"Eligible")/D12*100),"")) -> 100 | F12: =IFERROR(INDEX('Quotation Comparison'!$K$5:$K$100,MATCH(1,INDEX(('Quotation Comparison'!$B$5:$B$100=A12)*('Quotation Comparison'!$C$5:$C$100=B12),0),0)),"") -> 6 | G12: =IF(K12<>"Yes","",IFERROR(MIN(100,_xlfn.MINIFS('Quotation Comparison'!$K$5:$K$100,'Quotation Comparison'!$B$5:$B$100,A12,'Quotation Comparison'!$M$5:$M$100,"Yes",'Quotation Comparison'!$Q$5:$Q$100,"Eligible")/F12*100),"")) -> 100 | H12: 90 | I12: 80 | J12: =IF(K12<>"Yes","",IF(COUNT(E12,G12,H12,I12)<4,"",E12*30%+G12*25%+H12*25%+I12*20%)) -> 93.5 | K12: =IFERROR(INDEX('Quotation Comparison'!$M$5:$M$100,MATCH(1,INDEX(('Quotation Comparison'!$B$5:$B$100=A12)*('Quotation Comparison'!$C$5:$C$100=B12),0),0)),"Pending") -> Yes | L12: =IF(K12<>"Yes","Not Eligible",IF(J12="","Pending Evaluation",IF(J12>=80,"Recommended for Review","Alternative for Review"))) -> Recommended for Review
A13: PR-2026-005 | B13: SUP-010 | C13: Bearing World | D13: =IFERROR(INDEX('Quotation Comparison'!$J$5:$J$100,MATCH(1,INDEX(('Quotation Comparison'!$B$5:$B$100=A13)*('Quotation Comparison'!$C$5:$C$100=B13),0),0)),"") -> 3729 | E13: =IF(K13<>"Yes","",IFERROR(MIN(100,_xlfn.MINIFS('Quotation Comparison'!$J$5:$J$100,'Quotation Comparison'!$B$5:$B$100,A13,'Quotation Comparison'!$M$5:$M$100,"Yes",'Quotation Comparison'!$Q$5:$Q$100,"Eligible")/D13*100),"")) | F13: =IFERROR(INDEX('Quotation Comparison'!$K$5:$K$100,MATCH(1,INDEX(('Quotation Comparison'!$B$5:$B$100=A13)*('Quotation Comparison'!$C$5:$C$100=B13),0),0)),"") -> 9 | G13: =IF(K13<>"Yes","",IFERROR(MIN(100,_xlfn.MINIFS('Quotation Comparison'!$K$5:$K$100,'Quotation Comparison'!$B$5:$B$100,A13,'Quotation Comparison'!$M$5:$M$100,"Yes",'Quotation Comparison'!$Q$5:$Q$100,"Eligible")/F13*100),"")) | H13: 90 | I13: 80 | J13: =IF(K13<>"Yes","",IF(COUNT(E13,G13,H13,I13)<4,"",E13*30%+G13*25%+H13*25%+I13*20%)) | K13: =IFERROR(INDEX('Quotation Comparison'!$M$5:$M$100,MATCH(1,INDEX(('Quotation Comparison'!$B$5:$B$100=A13)*('Quotation Comparison'!$C$5:$C$100=B13),0),0)),"Pending") -> Pending | L13: =IF(K13<>"Yes","Not Eligible",IF(J13="","Pending Evaluation",IF(J13>=80,"Recommended for Review","Alternative for Review"))) -> Not Eligible
A14: PR-2026-005 | B14: SUP-011 | C14: Precision MRO | D14: =IFERROR(INDEX('Quotation Comparison'!$J$5:$J$100,MATCH(1,INDEX(('Quotation Comparison'!$B$5:$B$100=A14)*('Quotation Comparison'!$C$5:$C$100=B14),0),0)),"") -> 3736.56 | E14: =IF(K14<>"Yes","",IFERROR(MIN(100,_xlfn.MINIFS('Quotation Comparison'!$J$5:$J$100,'Quotation Comparison'!$B$5:$B$100,A14,'Quotation Comparison'!$M$5:$M$100,"Yes",'Quotation Comparison'!$Q$5:$Q$100,"Eligible")/D14*100),"")) -> 99.845848 | F14: =IFERROR(INDEX('Quotation Comparison'!$K$5:$K$100,MATCH(1,INDEX(('Quotation Comparison'!$B$5:$B$100=A14)*('Quotation Comparison'!$C$5:$C$100=B14),0),0)),"") -> 7 | G14: =IF(K14<>"Yes","",IFERROR(MIN(100,_xlfn.MINIFS('Quotation Comparison'!$K$5:$K$100,'Quotation Comparison'!$B$5:$B$100,A14,'Quotation Comparison'!$M$5:$M$100,"Yes",'Quotation Comparison'!$Q$5:$Q$100,"Eligible")/F14*100),"")) -> 85.714286 | H14: 88 | I14: 85 | J14: =IF(K14<>"Yes","",IF(COUNT(E14,G14,H14,I14)<4,"",E14*30%+G14*25%+H14*25%+I14*20%)) -> 90.382326 | K14: =IFERROR(INDEX('Quotation Comparison'!$M$5:$M$100,MATCH(1,INDEX(('Quotation Comparison'!$B$5:$B$100=A14)*('Quotation Comparison'!$C$5:$C$100=B14),0),0)),"Pending") -> Yes | L14: =IF(K14<>"Yes","Not Eligible",IF(J14="","Pending Evaluation",IF(J14>=80,"Recommended for Review","Alternative for Review"))) -> Recommended for Review
E15: =IF(OR(D15="",K15<>"Yes"),"",IFERROR(_xludf.MINIFS('Quotation Comparison'!$J$5:$J$100,'Quotation Comparison'!$B$5:$B$100,A15,'Quotation Comparison'!$M$5:$M$100,"Yes",'Quotation Comparison'!$Q$5:$Q$100,"Eligible")/D15*100,"")) | G15: =IF(OR(F15="",K15<>"Yes"),"",IFERROR(_xludf.MINIFS('Quotation Comparison'!$K$5:$K$100,'Quotation Comparison'!$B$5:$B$100,A15,'Quotation Comparison'!$M$5:$M$100,"Yes",'Quotation Comparison'!$Q$5:$Q$100,"Eligible")/F15*100,"")) | J15: =IF(OR(K15<>"Yes",E15="",G15="",H15="",I15=""),"",ROUND(E15*50%+G15*20%+H15*20%+I15*10%,1))
E16: =IF(OR(D16="",K16<>"Yes"),"",IFERROR(_xludf.MINIFS('Quotation Comparison'!$J$5:$J$100,'Quotation Comparison'!$B$5:$B$100,A16,'Quotation Comparison'!$M$5:$M$100,"Yes",'Quotation Comparison'!$Q$5:$Q$100,"Eligible")/D16*100,"")) | G16: =IF(OR(F16="",K16<>"Yes"),"",IFERROR(_xludf.MINIFS('Quotation Comparison'!$K$5:$K$100,'Quotation Comparison'!$B$5:$B$100,A16,'Quotation Comparison'!$M$5:$M$100,"Yes",'Quotation Comparison'!$Q$5:$Q$100,"Eligible")/F16*100,"")) | J16: =IF(OR(K16<>"Yes",E16="",G16="",H16="",I16=""),"",ROUND(E16*50%+G16*20%+H16*20%+I16*10%,1))
E17: =IF(OR(D17="",K17<>"Yes"),"",IFERROR(_xludf.MINIFS('Quotation Comparison'!$J$5:$J$100,'Quotation Comparison'!$B$5:$B$100,A17,'Quotation Comparison'!$M$5:$M$100,"Yes",'Quotation Comparison'!$Q$5:$Q$100,"Eligible")/D17*100,"")) | G17: =IF(OR(F17="",K17<>"Yes"),"",IFERROR(_xludf.MINIFS('Quotation Comparison'!$K$5:$K$100,'Quotation Comparison'!$B$5:$B$100,A17,'Quotation Comparison'!$M$5:$M$100,"Yes",'Quotation Comparison'!$Q$5:$Q$100,"Eligible")/F17*100,"")) | J17: =IF(OR(K17<>"Yes",E17="",G17="",H17="",I17=""),"",ROUND(E17*50%+G17*20%+H17*20%+I17*10%,1))
E18: =IF(OR(D18="",K18<>"Yes"),"",IFERROR(_xludf.MINIFS('Quotation Comparison'!$J$5:$J$100,'Quotation Comparison'!$B$5:$B$100,A18,'Quotation Comparison'!$M$5:$M$100,"Yes",'Quotation Comparison'!$Q$5:$Q$100,"Eligible")/D18*100,"")) | G18: =IF(OR(F18="",K18<>"Yes"),"",IFERROR(_xludf.MINIFS('Quotation Comparison'!$K$5:$K$100,'Quotation Comparison'!$B$5:$B$100,A18,'Quotation Comparison'!$M$5:$M$100,"Yes",'Quotation Comparison'!$Q$5:$Q$100,"Eligible")/F18*100,"")) | J18: =IF(OR(K18<>"Yes",E18="",G18="",H18="",I18=""),"",ROUND(E18*50%+G18*20%+H18*20%+I18*10%,1))
E19: =IF(OR(D19="",K19<>"Yes"),"",IFERROR(_xludf.MINIFS('Quotation Comparison'!$J$5:$J$100,'Quotation Comparison'!$B$5:$B$100,A19,'Quotation Comparison'!$M$5:$M$100,"Yes",'Quotation Comparison'!$Q$5:$Q$100,"Eligible")/D19*100,"")) | G19: =IF(OR(F19="",K19<>"Yes"),"",IFERROR(_xludf.MINIFS('Quotation Comparison'!$K$5:$K$100,'Quotation Comparison'!$B$5:$B$100,A19,'Quotation Comparison'!$M$5:$M$100,"Yes",'Quotation Comparison'!$Q$5:$Q$100,"Eligible")/F19*100,"")) | J19: =IF(OR(K19<>"Yes",E19="",G19="",H19="",I19=""),"",ROUND(E19*50%+G19*20%+H19*20%+I19*10%,1))
E20: =IF(OR(D20="",K20<>"Yes"),"",IFERROR(_xludf.MINIFS('Quotation Comparison'!$J$5:$J$100,'Quotation Comparison'!$B$5:$B$100,A20,'Quotation Comparison'!$M$5:$M$100,"Yes",'Quotation Comparison'!$Q$5:$Q$100,"Eligible")/D20*100,"")) | G20: =IF(OR(F20="",K20<>"Yes"),"",IFERROR(_xludf.MINIFS('Quotation Comparison'!$K$5:$K$100,'Quotation Comparison'!$B$5:$B$100,A20,'Quotation Comparison'!$M$5:$M$100,"Yes",'Quotation Comparison'!$Q$5:$Q$100,"Eligible")/F20*100,"")) | J20: =IF(OR(K20<>"Yes",E20="",G20="",H20="",I20=""),"",ROUND(E20*50%+G20*20%+H20*20%+I20*10%,1))
E21: =IF(OR(D21="",K21<>"Yes"),"",IFERROR(_xludf.MINIFS('Quotation Comparison'!$J$5:$J$100,'Quotation Comparison'!$B$5:$B$100,A21,'Quotation Comparison'!$M$5:$M$100,"Yes",'Quotation Comparison'!$Q$5:$Q$100,"Eligible")/D21*100,"")) | G21: =IF(OR(F21="",K21<>"Yes"),"",IFERROR(_xludf.MINIFS('Quotation Comparison'!$K$5:$K$100,'Quotation Comparison'!$B$5:$B$100,A21,'Quotation Comparison'!$M$5:$M$100,"Yes",'Quotation Comparison'!$Q$5:$Q$100,"Eligible")/F21*100,"")) | J21: =IF(OR(K21<>"Yes",E21="",G21="",H21="",I21=""),"",ROUND(E21*50%+G21*20%+H21*20%+I21*10%,1))
E22: =IF(OR(D22="",K22<>"Yes"),"",IFERROR(_xludf.MINIFS('Quotation Comparison'!$J$5:$J$100,'Quotation Comparison'!$B$5:$B$100,A22,'Quotation Comparison'!$M$5:$M$100,"Yes",'Quotation Comparison'!$Q$5:$Q$100,"Eligible")/D22*100,"")) | G22: =IF(OR(F22="",K22<>"Yes"),"",IFERROR(_xludf.MINIFS('Quotation Comparison'!$K$5:$K$100,'Quotation Comparison'!$B$5:$B$100,A22,'Quotation Comparison'!$M$5:$M$100,"Yes",'Quotation Comparison'!$Q$5:$Q$100,"Eligible")/F22*100,"")) | J22: =IF(OR(K22<>"Yes",E22="",G22="",H22="",I22=""),"",ROUND(E22*50%+G22*20%+H22*20%+I22*10%,1))
E23: =IF(OR(D23="",K23<>"Yes"),"",IFERROR(_xludf.MINIFS('Quotation Comparison'!$J$5:$J$100,'Quotation Comparison'!$B$5:$B$100,A23,'Quotation Comparison'!$M$5:$M$100,"Yes",'Quotation Comparison'!$Q$5:$Q$100,"Eligible")/D23*100,"")) | G23: =IF(OR(F23="",K23<>"Yes"),"",IFERROR(_xludf.MINIFS('Quotation Comparison'!$K$5:$K$100,'Quotation Comparison'!$B$5:$B$100,A23,'Quotation Comparison'!$M$5:$M$100,"Yes",'Quotation Comparison'!$Q$5:$Q$100,"Eligible")/F23*100,"")) | J23: =IF(OR(K23<>"Yes",E23="",G23="",H23="",I23=""),"",ROUND(E23*50%+G23*20%+H23*20%+I23*10%,1))
E24: =IF(OR(D24="",K24<>"Yes"),"",IFERROR(_xludf.MINIFS('Quotation Comparison'!$J$5:$J$100,'Quotation Comparison'!$B$5:$B$100,A24,'Quotation Comparison'!$M$5:$M$100,"Yes",'Quotation Comparison'!$Q$5:$Q$100,"Eligible")/D24*100,"")) | G24: =IF(OR(F24="",K24<>"Yes"),"",IFERROR(_xludf.MINIFS('Quotation Comparison'!$K$5:$K$100,'Quotation Comparison'!$B$5:$B$100,A24,'Quotation Comparison'!$M$5:$M$100,"Yes",'Quotation Comparison'!$Q$5:$Q$100,"Eligible")/F24*100,"")) | J24: =IF(OR(K24<>"Yes",E24="",G24="",H24="",I24=""),"",ROUND(E24*50%+G24*20%+H24*20%+I24*10%,1))
E25: =IF(OR(D25="",K25<>"Yes"),"",IFERROR(_xludf.MINIFS('Quotation Comparison'!$J$5:$J$100,'Quotation Comparison'!$B$5:$B$100,A25,'Quotation Comparison'!$M$5:$M$100,"Yes",'Quotation Comparison'!$Q$5:$Q$100,"Eligible")/D25*100,"")) | G25: =IF(OR(F25="",K25<>"Yes"),"",IFERROR(_xludf.MINIFS('Quotation Comparison'!$K$5:$K$100,'Quotation Comparison'!$B$5:$B$100,A25,'Quotation Comparison'!$M$5:$M$100,"Yes",'Quotation Comparison'!$Q$5:$Q$100,"Eligible")/F25*100,"")) | J25: =IF(OR(K25<>"Yes",E25="",G25="",H25="",I25=""),"",ROUND(E25*50%+G25*20%+H25*20%+I25*10%,1))
E26: =IF(OR(D26="",K26<>"Yes"),"",IFERROR(_xludf.MINIFS('Quotation Comparison'!$J$5:$J$100,'Quotation Comparison'!$B$5:$B$100,A26,'Quotation Comparison'!$M$5:$M$100,"Yes",'Quotation Comparison'!$Q$5:$Q$100,"Eligible")/D26*100,"")) | G26: =IF(OR(F26="",K26<>"Yes"),"",IFERROR(_xludf.MINIFS('Quotation Comparison'!$K$5:$K$100,'Quotation Comparison'!$B$5:$B$100,A26,'Quotation Comparison'!$M$5:$M$100,"Yes",'Quotation Comparison'!$Q$5:$Q$100,"Eligible")/F26*100,"")) | J26: =IF(OR(K26<>"Yes",E26="",G26="",H26="",I26=""),"",ROUND(E26*50%+G26*20%+H26*20%+I26*10%,1))
... E100: =IF(OR(D100="",K100<>"Yes"),"",IFERROR(_xludf.MINIFS('Quotation Comparison'!$J$5:$J$100,'Quotation Comparison'!$B$5:$B$100,A100,'Quotation Comparison'!$M$5:$M$100,"Yes",'Quotation Comparison'!$Q$5:$Q$100,"Eligible")/D100*100,"")) | G100: =IF(OR(F100="",K100<>"Yes"),"",IFERROR(_xludf.MINIFS('Quotation Comparison'!$K$5:$K$100,'Quotation Comparison'!$B$5:$B$100,A100,'Quotation Comparison'!$M$5:$M$100,"Yes",'Quotation Comparison'!$Q$5:$Q$100,"Eligible")/F100*100,"")) | J100: =IF(OR(K100<>"Yes",E100="",G100="",H100="",I100=""),"",ROUND(E100*50%+G100*20%+H100*20%+I100*10%,1))

Sheet Award Recommendation
A1: Award Recommendation
A2: Decision-support summary for review and approval. Final supplier selection must follow company policy and authorized approval.
A4: Requisition ID | B4: Item / Service Description | C4: Recommended Supplier | D4: Recommended Total Cost (SAR) | E4: Lowest Compliant Cost (SAR) | F4: Potential Cost Difference (SAR) | G4: Recommendation Rationale | H4: Approval Status
A5: PR-2026-001 | B5: Industrial Safety Gloves | C5: =IFERROR(INDEX('Supplier Evaluation'!$C$5:$C$100,MATCH(1,INDEX(('Supplier Evaluation'!$A$5:$A$100=A5)*('Supplier Evaluation'!$K$5:$K$100="Yes")*('Supplier Evaluation'!$J$5:$J$100=_xlfn.MAXIFS('Supplier Evaluation'!$J$5:$J$100,'Supplier Evaluation'!$A$5:$A$100,A5,'Supplier Evaluation'!$K$5:$K$100,"Yes")),0),0)),"Review Required") -> Eastern Safety Trading | D5: =IFERROR(INDEX('Supplier Evaluation'!$D$5:$D$100,MATCH(1,INDEX(('Supplier Evaluation'!$A$5:$A$100=A5)*('Supplier Evaluation'!$C$5:$C$100=C5),0),0)),"") -> 5020.4 | E5: =IFERROR(_xlfn.MINIFS('Quotation Comparison'!$J$5:$J$100,'Quotation Comparison'!$B$5:$B$100,A5,'Quotation Comparison'!$M$5:$M$100,"Yes",'Quotation Comparison'!$Q$5:$Q$100,"Eligible"),"") -> 4895.7 | F5: =IF(OR(D5="",E5=""),"",D5-E5) -> 124.7 | G5: =IF(C5="Review Required","Review compliant quotations, delivery requirements, and scoring before recommendation.",IF(C5="","Review evaluation results before recommendation.","Recommended based on weighted evaluation; confirm specifications, commercial terms, and approvals.")) -> Recommended based on weighted evaluation; confirm specifications, commercial terms, and approvals.
A6: PR-2026-002 | B6: LED High-Bay Lights | C6: =IFERROR(INDEX('Supplier Evaluation'!$C$5:$C$100,MATCH(1,INDEX(('Supplier Evaluation'!$A$5:$A$100=A6)*('Supplier Evaluation'!$K$5:$K$100="Yes")*('Supplier Evaluation'!$J$5:$J$100=_xlfn.MAXIFS('Supplier Evaluation'!$J$5:$J$100,'Supplier Evaluation'!$A$5:$A$100,A6,'Supplier Evaluation'!$K$5:$K$100,"Yes")),0),0)),"Review Required") -> BrightTech Electrical | D6: =IFERROR(INDEX('Supplier Evaluation'!$D$5:$D$100,MATCH(1,INDEX(('Supplier Evaluation'!$A$5:$A$100=A6)*('Supplier Evaluation'!$C$5:$C$100=C6),0),0)),"") -> 16668.6 | E6: =IFERROR(_xlfn.MINIFS('Quotation Comparison'!$J$5:$J$100,'Quotation Comparison'!$B$5:$B$100,A6,'Quotation Comparison'!$M$5:$M$100,"Yes",'Quotation Comparison'!$Q$5:$Q$100,"Eligible"),"") -> 16668.6 | F6: =IF(OR(D6="",E6=""),"",D6-E6) -> 0 | G6: =IF(C6="Review Required","Review compliant quotations, delivery requirements, and scoring before recommendation.",IF(C6="","Review evaluation results before recommendation.","Recommended based on weighted evaluation; confirm specifications, commercial terms, and approvals.")) -> Recommended based on weighted evaluation; confirm specifications, commercial terms, and approvals.
A7: PR-2026-003 | B7: Wireless Barcode Scanners | C7: =IFERROR(INDEX('Supplier Evaluation'!$C$5:$C$100,MATCH(1,INDEX(('Supplier Evaluation'!$A$5:$A$100=A7)*('Supplier Evaluation'!$K$5:$K$100="Yes")*('Supplier Evaluation'!$J$5:$J$100=_xlfn.MAXIFS('Supplier Evaluation'!$J$5:$J$100,'Supplier Evaluation'!$A$5:$A$100,A7,'Supplier Evaluation'!$K$5:$K$100,"Yes")),0),0)),"Review Required") -> ScanPro Systems | D7: =IFERROR(INDEX('Supplier Evaluation'!$D$5:$D$100,MATCH(1,INDEX(('Supplier Evaluation'!$A$5:$A$100=A7)*('Supplier Evaluation'!$C$5:$C$100=C7),0),0)),"") -> 9196.32 | E7: =IFERROR(_xlfn.MINIFS('Quotation Comparison'!$J$5:$J$100,'Quotation Comparison'!$B$5:$B$100,A7,'Quotation Comparison'!$M$5:$M$100,"Yes",'Quotation Comparison'!$Q$5:$Q$100,"Eligible"),"") -> 8715 | F7: =IF(OR(D7="",E7=""),"",D7-E7) -> 481.32 | G7: =IF(C7="Review Required","Review compliant quotations, delivery requirements, and scoring before recommendation.",IF(C7="","Review evaluation results before recommendation.","Recommended based on weighted evaluation; confirm specifications, commercial terms, and approvals.")) -> Recommended based on weighted evaluation; confirm specifications, commercial terms, and approvals.
A8: PR-2026-005 | B8: Industrial Bearings | C8: =IFERROR(INDEX('Supplier Evaluation'!$C$5:$C$100,MATCH(1,INDEX(('Supplier Evaluation'!$A$5:$A$100=A8)*('Supplier Evaluation'!$K$5:$K$100="Yes")*('Supplier Evaluation'!$J$5:$J$100=_xlfn.MAXIFS('Supplier Evaluation'!$J$5:$J$100,'Supplier Evaluation'!$A$5:$A$100,A8,'Supplier Evaluation'!$K$5:$K$100,"Yes")),0),0)),"Review Required") -> Gulf Industrial Supply | D8: =IFERROR(INDEX('Supplier Evaluation'!$D$5:$D$100,MATCH(1,INDEX(('Supplier Evaluation'!$A$5:$A$100=A8)*('Supplier Evaluation'!$C$5:$C$100=C8),0),0)),"") -> 3730.8 | E8: =IFERROR(_xlfn.MINIFS('Quotation Comparison'!$J$5:$J$100,'Quotation Comparison'!$B$5:$B$100,A8,'Quotation Comparison'!$M$5:$M$100,"Yes",'Quotation Comparison'!$Q$5:$Q$100,"Eligible"),"") -> 3730.8 | F8: =IF(OR(D8="",E8=""),"",D8-E8) -> 0 | G8: =IF(C8="Review Required","Review compliant quotations, delivery requirements, and scoring before recommendation.",IF(C8="","Review evaluation results before recommendation.","Recommended based on weighted evaluation; confirm specifications, commercial terms, and approvals.")) -> Recommended based on weighted evaluation; confirm specifications, commercial terms, and approvals.

Sheet Lists
A1: Reference Lists
A2: Controlled values used by dropdowns throughout the workbook. Edit carefully to preserve formula logic.
A4: Priority | B4: Requisition Status | C4: RFQ Status | D4: Supplier Response | E4: Compliance Status
A5: Low | B5: Draft | C5: Draft | D5: Pending | E5: Compliant
A6: Normal | B6: Submitted | C6: Sent | D6: Received | E6: Non-Compliant
A7: High | B7: Approved | C7: Responses Received | D7: Declined | E7: Pending Review
A8: Critical | B8: Rejected | C8: Closed | D8: No Response
B9: Cancelled | C9: Cancelled

Sheet Read Me
A1: Read Me | RFQ & Supplier Quotation Evaluation System
A2: A practical Excel 2019 portfolio project for procurement operations and supplier evaluation.
A4: Project Purpose | B4: This workbook simulates a procurement workflow from internal purchase requisition through RFQ tracking, quotation comparison, supplier evaluation, and award recommendation.
A5: Compatibility | B5: Designed for Microsoft Excel 2019. Uses standard formulas such as IF, IFERROR, INDEX, MATCH, COUNTIF, COUNTIFS, and AGGREGATE. No macros are required.
A6: Workbook Structure | B6: Dashboard: summary KPIs and requisition status. Purchase Requisitions: internal demand register. RFQ Register: supplier invitation and response tracking. Quotation Comparison: total cost and compliance checks. Supplier Evaluation: weighted scorecard. Award Recommendation: decision support. Lists: dropdown reference values.
A7: Calculation Assumptions | B7: Total quoted cost = unit price × quantity × (1 − discount) × (1 + VAT rate) + shipping. This is an illustrative calculation; confirm the appropriate tax treatment and whether shipping is taxable under the applicable policy before real use.
A8: Scoring Model | B8: Illustrative weights: price 50%, lead time 20%, quality 20%, payment terms 10%. A non-compliant quotation is not eligible regardless of its weighted score. Scores and weights should be approved and adapted to organizational policy.
A9: Sample Data | B9: All supplier names, people, purchase requests, prices, dates, and transactions are fictional examples created for demonstration. The data do not represent actual companies or market quotations.
A10: How to Extend | B10: Add new records beneath the existing Excel tables. Extend formulas and validation rules when adding rows beyond the prepared sample range. Keep Requisition IDs, RFQ IDs, and Supplier IDs unique and consistent.
A11: Important Limitation | B11: This workbook is a portfolio decision-support model, not an ERP system or an authorized procurement approval tool. The recommendation must be reviewed by the appropriate procurement and budget owners.
A12: Author | B12: Bandar Al Radhi
